LICENSE
MANIFEST.in
README.rst
pyproject.toml
setup.cfg
setup.py
py2/__init__.py
py2/asyncfile.py
py2/config.py
py2/dispycos.py
py2/dispycosnode.py
py2/httpd.py
py2/netpycos.py
py2/data/Dockerfile
py2/data/cluster.html
py2/data/favicon.ico
py2/data/jquery.js
py2/data/node.html
py2/data/pycos.css
py2/data/pycos.js
py2/data/server.html
py2/examples/README
py2/examples/asyncoro2pycos.sed
py2/examples/channel.py
py2/examples/chat_chan_client.py
py2/examples/chat_chan_server.py
py2/examples/chat_client.py
py2/examples/chat_server.py
py2/examples/chat_server2.py
py2/examples/chat_sock_client.py
py2/examples/chat_sock_server.py
py2/examples/client_server.py
py2/examples/dispycos_client1.py
py2/examples/dispycos_client10.py
py2/examples/dispycos_client2.py
py2/examples/dispycos_client3.py
py2/examples/dispycos_client4.py
py2/examples/dispycos_client5.py
py2/examples/dispycos_client5_proc.py
py2/examples/dispycos_client7.py
py2/examples/dispycos_client8.py
py2/examples/dispycos_client9_node.py
py2/examples/dispycos_client9_server.py
py2/examples/dispycos_cloud_computing.py
py2/examples/dispycos_httpd1.py
py2/examples/dispycos_httpd2.py
py2/examples/dispycos_kbd_int.py
py2/examples/dispycos_live_analytics.py
py2/examples/dispycos_live_analytics_channel.py
py2/examples/dispycos_mas.py
py2/examples/dispycos_mem_servers.py
py2/examples/dispycos_remote_scheduler.py
py2/examples/dispycos_ssh_ec2.py
py2/examples/hotswap.py
py2/examples/hotswap_funcs.py
py2/examples/node_update_script.py
py2/examples/pico_client_task.py
py2/examples/pico_service_task.py
py2/examples/pipe_csum.py
py2/examples/pipe_grep.py
py2/examples/remote_channel_client.py
py2/examples/remote_channel_server.py
py2/examples/remote_task_client.py
py2/examples/remote_task_server.py
py2/examples/rps_log_watch_client.py
py2/examples/rps_log_watch_server.py
py2/examples/rps_monitor_client.py
py2/examples/rps_monitor_server.py
py2/examples/rps_node_client.py
py2/examples/rps_node_server.py
pycos.egg-info/PKG-INFO
pycos.egg-info/SOURCES.txt
pycos.egg-info/dependency_links.txt
pycos.egg-info/top_level.txt