Metadata-Version: 2.1
Name: pycos
Version: 4.12.2
Summary: Concurrent, Asynchronous, Distributed, Communicating Tasks with Python
Home-page: https://pycos.org
Author: Giridhar Pemmasani
Author-email: pgiri@yahoo.com
License: Apache 2.0
Keywords: concurrency,asynchronous,network programming,distributed,tasks,message passing
Platform: any
Classifier: Development Status :: 5 - Production/Stable
Classifier: Intended Audience :: Developers
Classifier: Intended Audience :: Science/Research
Classifier: License :: OSI Approved :: Apache Software License
Classifier: Operating System :: OS Independent
Classifier: Programming Language :: Python :: 2
Classifier: Programming Language :: Python :: 2.7
Classifier: Programming Language :: Python :: 3
Classifier: Programming Language :: Python :: 3.1
Classifier: Topic :: Scientific/Engineering
Classifier: Topic :: Software Development :: Libraries
License-File: LICENSE
